psgtray/LICENSE.txt
psgtray/README.md
psgtray/__init__.py
psgtray/__main__.py
psgtray/psgtray.py
psgtray-5.0.0.dist-info/LICENSE.txt
psgtray-5.0.0.dist-info/METADATA
psgtray-5.0.0.dist-info/WHEEL
psgtray-5.0.0.dist-info/entry_points.txt
psgtray-5.0.0.dist-info/top_level.txt
psgtray-5.0.0.dist-info/RECORD
